{
  "@microsoft/generator-sharepoint": {
    "plusBeta": false,
    "isCreatingSolution": true,
    "nodeVersion": "18.19.0",
    "sdksVersions": {
      "@microsoft/microsoft-graph-client": "3.0.2",
      "@microsoft/teams-js": "2.12.0"
    },
    "version": "1.18.2",
    "libraryName": "one-view-ace",
    "libraryId": "25a084f4-fbf9-48a7-83bb-c109610b4e79",
    "environment": "spo",
    "packageManager": "npm",
    "solutionName": "OneViewAce",
    "solutionShortDescription": "OneViewAce description",
    "skipFeatureDeployment": true,
    "isDomainIsolated": false,
    "componentType": "adaptiveCardExtension",
    "aceTemplateType": "Generic"
  }
}
